genomics_data_index/__init__.py
genomics_data_index/ete3treeview.py
genomics_data_index/api/__init__.py
genomics_data_index/api/query/GenomicsDataIndex.py
genomics_data_index/api/query/SamplesQuery.py
genomics_data_index/api/query/TreeBuilder.py
genomics_data_index/api/query/__init__.py
genomics_data_index/api/query/features/FeaturesComparator.py
genomics_data_index/api/query/features/FeaturesFromIndexComparator.py
genomics_data_index/api/query/features/MLSTFeaturesComparator.py
genomics_data_index/api/query/features/MutationFeaturesFromIndexComparator.py
genomics_data_index/api/query/features/SampleCategoriesClustererExperimental.py
genomics_data_index/api/query/features/__init__.py
genomics_data_index/api/query/impl/ClusterScorer.py
genomics_data_index/api/query/impl/DataFrameSamplesQuery.py
genomics_data_index/api/query/impl/ExperimentalTreeSamplesQuery.py
genomics_data_index/api/query/impl/KmerTreeSamplesQuery.py
genomics_data_index/api/query/impl/MutationTreeSamplesQuery.py
genomics_data_index/api/query/impl/QueriesCollection.py
genomics_data_index/api/query/impl/SamplesQueryIndex.py
genomics_data_index/api/query/impl/TreeBuilderKmers.py
genomics_data_index/api/query/impl/TreeBuilderReferenceMutations.py
genomics_data_index/api/query/impl/TreeSamplesQuery.py
genomics_data_index/api/query/impl/TreeSamplesQueryFactory.py
genomics_data_index/api/query/impl/WrappedSamplesQuery.py
genomics_data_index/api/query/impl/__init__.py
genomics_data_index/api/query/impl/cluster/ClusterScoreMRCAJaccard.py
genomics_data_index/api/query/impl/cluster/ClusterScoreMethod.py
genomics_data_index/api/query/impl/cluster/__init__.py
genomics_data_index/api/query/kind/IsaKind.py
genomics_data_index/api/query/kind/__init__.py
genomics_data_index/api/query/kind/isa/DelegateIsaKind.py
genomics_data_index/api/query/kind/isa/__init__.py
genomics_data_index/api/query/kind/isa/typing/ExperimentalSARSCov2ConstellationsTyper.py
genomics_data_index-0.9.2.dist-info/LICENSE
genomics_data_index-0.9.2.dist-info/METADATA
genomics_data_index-0.9.2.dist-info/WHEEL
genomics_data_index-0.9.2.dist-info/entry_points.txt
genomics_data_index-0.9.2.dist-info/top_level.txt
genomics_data_index-0.9.2.dist-info/RECORD
