Metadata-Version: 2.1
Name: genomics-data-index
Version: 0.9.2
Summary: Indexes genomics data (nucleotide variants, kmers, MLST) for fast querying of features.
Author-email: Aaron Petkau <aaron.petkau@gmail.com>
Project-URL: Homepage, https://github.com/apetkau/genomics-data-index
Project-URL: Bug Tracker, https://github.com/apetkau/genomics-data-index/issues
Classifier: Development Status :: 4 - Beta
Classifier: Environment :: Console
Classifier: License :: OSI Approved :: Apache Software License
Classifier: Intended Audience :: Science/Research
Classifier: Topic :: Scientific/Engineering
Classifier: Topic :: Scientific/Engineering :: Bio-Informatics
Classifier: Programming Language :: Python :: 3.8
Classifier: Programming Language :: Python :: 3.9
Classifier: Operating System :: POSIX :: Linux
Requires-Python: <3.10,>=3.8
License-File: LICENSE
Requires-Dist: biopython (>=1.70)
Requires-Dist: pandas (>=1.0.0)
Requires-Dist: numpy
Requires-Dist: scikit-bio
Requires-Dist: scipy (<1.9)
Requires-Dist: vcfpy
Requires-Dist: sqlalchemy
Requires-Dist: pymysql
Requires-Dist: requests
Requires-Dist: ete3
Requires-Dist: PyQt5
Requires-Dist: biocommons.seqrepo
Requires-Dist: click
Requires-Dist: click-config-file
Requires-Dist: coloredlogs
Requires-Dist: pyyaml
Requires-Dist: pyroaring
Requires-Dist: sourmash
Requires-Dist: pybedtools
Requires-Dist: snakemake
Requires-Dist: Jinja2
Requires-Dist: pathvalidate
Requires-Dist: pytest
Requires-Dist: zipp
Requires-Dist: packaging
